rclone_python/__init__.py
rclone_python/hash_types.py
rclone_python/logs.py
rclone_python/rclone.py
rclone_python/remote_types.py
rclone_python/utils.py
rclone_python-0.1.23.dist-info/licenses/LICENSE
rclone_python-0.1.23.dist-info/METADATA
rclone_python-0.1.23.dist-info/WHEEL
rclone_python-0.1.23.dist-info/top_level.txt
rclone_python-0.1.23.dist-info/RECORD
