Metadata-Version: 2.4
Name: rclone-python
Version: 0.1.23
Summary: A python wrapper for rclone.
Home-page: https://github.com/Johannes11833/rclone_python
Author: Johannes Gundlach
Keywords: rclone,wrapper,cloud sync
Classifier: Programming Language :: Python :: 3
Classifier: License :: OSI Approved :: MIT License
Classifier: Operating System :: OS Independent
Requires-Python: >=3.6
License-File: LICENSE
Requires-Dist: rich
Dynamic: author
Dynamic: classifier
Dynamic: description
Dynamic: description-content-type
Dynamic: home-page
Dynamic: keywords
Dynamic: license-file
Dynamic: requires-dist
Dynamic: requires-python
Dynamic: summary
